taipy_utils/__init__.py
taipy_utils/decorators.py
taipy_utils-0.1.1.dist-info/METADATA
taipy_utils-0.1.1.dist-info/WHEEL
taipy_utils-0.1.1.dist-info/licenses/LICENSE
taipy_utils-0.1.1.dist-info/RECORD
