Metadata-Version: 2.4
Name: taipy-utils
Version: 0.1.1
Summary: Utility decorators and helpers for Taipy GUI applications
Project-URL: Homepage, https://github.com/enarroied/taipy_utils
Project-URL: Repository, https://github.com/enarroied/taipy_utils
Author-email: Eric Narro <eric.narro.ied@gmail.com>
License-File: LICENSE
Keywords: decorators,gui,taipy,utilities
Classifier: Development Status :: 3 - Alpha
Classifier: Intended Audience :: Developers
Classifier: Programming Language :: Python :: 3
Classifier: Programming Language :: Python :: 3.9
Classifier: Programming Language :: Python :: 3.10
Classifier: Programming Language :: Python :: 3.11
Classifier: Programming Language :: Python :: 3.12
Requires-Python: <3.13,>=3.9
Requires-Dist: taipy>=4.1.0
